{
  "SAUCE SOJA": "SAUCE SOJA SUCRÉE 800 DOSETTES 10ML HANABI",

  "OIGNON JAUNE": "OIGNON FRIT 500G",

  "ALGUE": "ALGUE NORI GRILLEE TEMAKI 100 PCS",
  "ALGUE NORI": "ALGUE NORI GRILLEE TEMAKI 100 PCS",
  "ALGUE NORI (TEMAKI)": "ALGUE NORI GRILLEE TEMAKI 100 PCS",

  "OIGNONS FRITS": "OIGNONS FRITS SANS GLUTEN 500G",
  "OIGNON FRIT": "OIGNONS FRITS SANS GLUTEN 500G",
  "OIGNONS FRITS (TOPPING)": "OIGNONS FRITS SANS GLUTEN 500G",

  "SHICHIMI": "MELANGE 7 EPICES / SHICHIMI TOGARASHI 300g",

  "AVOCAT": "PUREE AVEC MORCEAUX D’AVOCAT 1KG",

  "SAUCE UNAGI": "SAUCE ANGUILLE / UNAGI SAUCE 2KG",

  "MAYONNAISE SPICY": "SAUCE SRIRACHA SAVEUR MAYO (A) 440ML PET",
  "MAYO": "SAUCE SRIRACHA SAVEUR MAYO (A) 440ML PET"
}
